unirt/__init__.py
unirt/amplify_doc_mcp_server/__init__.py
unirt/amplify_doc_mcp_server/models.py
unirt/amplify_doc_mcp_server/server.py
unirt/amplify_doc_mcp_server/util.py
unirt_amplify_doc_mcp_server-0.0.3.dist-info/METADATA
unirt_amplify_doc_mcp_server-0.0.3.dist-info/WHEEL
unirt_amplify_doc_mcp_server-0.0.3.dist-info/entry_points.txt
unirt_amplify_doc_mcp_server-0.0.3.dist-info/RECORD
