Metadata-Version: 2.4
Name: unirt.amplify-doc-mcp-server
Version: 0.0.3
Summary: An Model Context Protocol (MCP) server for AWS Amplify Gen 2 Documentation
Requires-Python: >=3.13
Requires-Dist: beautifulsoup4>=4.12.0
Requires-Dist: httpx>=0.27.0
Requires-Dist: loguru>=0.7.0
Requires-Dist: markdownify>=1.1.0
Requires-Dist: mcp[cli]>=1.6.0
Requires-Dist: pydantic>=2.10.6
